catops/__init__.py
catops/__version__.py
catops/auth.py
catops/dispatcher.py
catops/helpers.py
catops/install.py
catops/parser.py
catops/plugin.py
catops/slack_handler.py
catops/templates/SlackHandler-demo/SlackHandler_demo.py
catops/templates/SlackHandler-demo/tokens.json
catops/templates/aws-bot/README.md
catops/templates/aws-bot/handler.py
catops/templates/aws-bot/package-lock.json
catops/templates/aws-bot/package.json
catops/templates/aws-bot/requirements.txt
catops/templates/aws-bot/serverless.yml
catops/templates/aws-bot/tokens.json
catops/templates/aws-slash/README.md
catops/templates/aws-slash/data.json
catops/templates/aws-slash/handler.py
catops/templates/aws-slash/package-lock.json
catops/templates/aws-slash/package.json
catops/templates/aws-slash/requirements.txt
catops/templates/aws-slash/serverless.yml
catops/templates/aws-slash/tokens.json
catops/templates/slack-logger/README.md
catops/templates/slack-logger/handler.py
catops/templates/slack-logger/package-lock.json
catops/templates/slack-logger/package.json
catops/templates/slack-logger/requirements.txt
catops/templates/slack-logger/serverless.yml
catops/templates/slack-logger/tokens.json
catops-1.0.0.dist-info/METADATA
catops-1.0.0.dist-info/RECORD
catops-1.0.0.dist-info/WHEEL
catops-1.0.0.dist-info/entry_points.txt
catops-1.0.0.dist-info/top_level.txt
