Metadata-Version: 2.1
Name: catops
Version: 1.0.0
Summary: Highly trained cats for managing servers.
Home-page: https://github.com/bboxx/CatOps
Author: George Punter
Author-email: info@bboxx.co.uk
License: MIT
Platform: UNKNOWN
Classifier: License :: OSI Approved :: MIT License
Classifier: Programming Language :: Python
Classifier: Programming Language :: Python :: 2
Classifier: Programming Language :: Python :: 2.7
Classifier: Programming Language :: Python :: 3
Classifier: Programming Language :: Python :: 3.4
Classifier: Programming Language :: Python :: 3.5
Classifier: Programming Language :: Python :: 3.6
Classifier: Programming Language :: Python :: Implementation :: CPython
Classifier: Programming Language :: Python :: Implementation :: PyPy
Requires-Python: >=2.7.0
Requires-Dist: requests
Requires-Dist: six
Requires-Dist: slacker
